hardcode_haml/__init__.py
hardcode_haml/main.py
hardcode_haml/parser.py
hardcode_haml/primitives.py
hardcode_haml/lang/__init__.py
hardcode_haml/lang/c.py
hardcode_haml/lang/cpp.py
hardcode_haml/lang/python.py
hardcode_haml-0.3.0.dist-info/COPYING
hardcode_haml-0.3.0.dist-info/METADATA
hardcode_haml-0.3.0.dist-info/WHEEL
hardcode_haml-0.3.0.dist-info/entry_points.txt
hardcode_haml-0.3.0.dist-info/top_level.txt
hardcode_haml-0.3.0.dist-info/RECORD
