Metadata-Version: 2.1
Name: hardcode-haml
Version: 0.3.0
Summary: Haml for hardcore coders (and C++/C/... projects)
Home-page: http://www.chaossource.net/hardcode_haml/
Author: Thammi
Author-email: thammi@chaossource.net
License: AGPLv3
Keywords: haml template html web
Classifier: Development Status :: 5 - Production/Stable
Classifier: Intended Audience :: Developers
Classifier: Programming Language :: C++
Classifier: Programming Language :: C
Classifier: Programming Language :: Python
Classifier: Topic :: Internet :: WWW/HTTP :: Dynamic Content
Classifier: Topic :: Software Development :: Pre-processors
Classifier: Topic :: Text Processing :: Markup :: HTML
Classifier: Environment :: Console
Classifier: License :: OSI Approved :: GNU Affero General Public License v3 or later (AGPLv3+)
License-File: COPYING
